auto_lrc/__init__.py
auto_lrc/cli.py
auto_lrc/cli_v2.py
auto_lrc/lrc.py
auto_lrc-3.0.0.dist-info/METADATA
auto_lrc-3.0.0.dist-info/WHEEL
auto_lrc-3.0.0.dist-info/entry_points.txt
auto_lrc-3.0.0.dist-info/RECORD
